khalinox/__init__.py
khalinox/config.py
khalinox/hive.py
khalinox/utils.py
khalinox/webhdfs.py
khalinox-1.1.3.dist-info/WHEEL
khalinox-1.1.3.dist-info/METADATA
khalinox-1.1.3.dist-info/RECORD
