Metadata-Version: 2.1
Name: khalinox
Version: 1.1.3
Summary: 
Author: Khalid
Author-email: khalid.chakhmoun@gmail.com
Requires-Python: >=3.8,<4.0
Classifier: Programming Language :: Python :: 3
Classifier: Programming Language :: Python :: 3.10
Classifier: Programming Language :: Python :: 3.8
Classifier: Programming Language :: Python :: 3.9
Requires-Dist: JayDeBeApi (>=1.2.3,<2.0.0)
Requires-Dist: cryptography (>=3.4.7,<4.0.0)
Requires-Dist: hdfs (>=2.6.0,<3.0.0)
Requires-Dist: loguru (>=0.5.3,<0.6.0)
Requires-Dist: pydantic (>=1.8.1,<2.0.0)
Requires-Dist: requests (>=2.25.1,<3.0.0)
Requires-Dist: toolz (>=0.11.1,<0.12.0)
